cloudmesh_aws-4.1.8-py3.8-nspkg.pth
cloudmesh/aws/__init__.py
cloudmesh/aws/__version__.py
cloudmesh/aws/compute/AwsFlavors-Gregor.py
cloudmesh/aws/compute/AwsFlavors-dev.py
cloudmesh/aws/compute/AwsFlavors.py
cloudmesh/aws/compute/Provider-dev.py
cloudmesh/aws/compute/Provider.py
cloudmesh/aws/compute/__init__.py
cloudmesh/aws/compute/gregor_flavor.py
cloudmesh/aws/compute/test_boto.py
cloudmesh_aws-4.1.8.dist-info/LICENSE
cloudmesh_aws-4.1.8.dist-info/METADATA
cloudmesh_aws-4.1.8.dist-info/WHEEL
cloudmesh_aws-4.1.8.dist-info/namespace_packages.txt
cloudmesh_aws-4.1.8.dist-info/top_level.txt
cloudmesh_aws-4.1.8.dist-info/RECORD
